{
  "group": "fantastical_fruits",
  "type": "minecraft:crafting_shaped",
  "pattern": [
    "01",
    "23"
  ],
  "key": {
    "0": {
      "item": "fantastical_fruits:stripped_aspen_log"
    },
    "1": {
      "item": "fantastical_fruits:stripped_aspen_log"
    },
    "2": {
      "item": "fantastical_fruits:stripped_aspen_log"
    },
    "3": {
      "item": "fantastical_fruits:stripped_aspen_log"
    }
  },
  "result": {
    "item": "fantastical_fruits:stripped_aspen_wood",
    "count": 3
  }
}